bda.plone.orders-2.0b2-py3.9-nspkg.pth
bda/plone/orders/__init__.py
bda/plone/orders/catalogfactories.py
bda/plone/orders/checkout.py
bda/plone/orders/common.py
bda/plone/orders/configure.zcml
bda/plone/orders/contacts.py
bda/plone/orders/events.py
bda/plone/orders/i18n.sh
bda/plone/orders/indexer.py
bda/plone/orders/localroles.py
bda/plone/orders/mailnotify.py
bda/plone/orders/mailtemplates.py
bda/plone/orders/permissions.py
bda/plone/orders/permissions.zcml
bda/plone/orders/profiles.zcml
bda/plone/orders/setuphandlers.py
bda/plone/orders/subscriber.py
bda/plone/orders/transitions.py
bda/plone/orders/upgrades.py
bda/plone/orders/upgrades.zcml
bda/plone/orders/vocabularies.py
bda/plone/orders/browser/__init__.py
bda/plone/orders/browser/bookings.py
bda/plone/orders/browser/common.py
bda/plone/orders/browser/configure.zcml
bda/plone/orders/browser/contacts.py
bda/plone/orders/browser/dropdown.py
bda/plone/orders/browser/export.py
bda/plone/orders/browser/invoice.py
bda/plone/orders/browser/mailtemplates.py
bda/plone/orders/browser/notify_customers.py
bda/plone/orders/browser/order.py
bda/plone/orders/browser/orders.py
bda/plone/orders/browser/views.py
bda/plone/orders/browser/forms/mailtemplates.yaml
bda/plone/orders/browser/forms/notify_customers.yaml
bda/plone/orders/browser/forms/orders_export.yaml
bda/plone/orders/browser/resources/bookings.png
bda/plone/orders/browser/resources/cross.png
bda/plone/orders/browser/resources/delete.png
bda/plone/orders/browser/resources/invoice.png
bda/plone/orders/browser/resources/invoices.png
bda/plone/orders/browser/resources/jquery-barcode.js
bda/plone/orders/browser/resources/notify_customers.png
bda/plone/orders/browser/resources/order.png
bda/plone/orders/browser/resources/orders.css
bda/plone/orders/browser/resources/orders.css.map
bda/plone/orders/browser/resources/orders.js
bda/plone/orders/browser/resources/orders.min.css
bda/plone/orders/browser/resources/orders.png
bda/plone/orders/browser/resources/pencil.png
bda.plone.orders-2.0b2.dist-info/LICENSE.rst
bda.plone.orders-2.0b2.dist-info/LICENSE_GPL.rst
bda.plone.orders-2.0b2.dist-info/METADATA
bda.plone.orders-2.0b2.dist-info/WHEEL
bda.plone.orders-2.0b2.dist-info/namespace_packages.txt
bda.plone.orders-2.0b2.dist-info/top_level.txt
bda.plone.orders-2.0b2.dist-info/RECORD
