Metadata-Version: 2.1
Name: bda.plone.orders
Version: 2.0b2
Summary: Orders persistence and backoffice UI for bda.plone.shop
Author: BlueDynamics Alliance
Author-email: dev@bluedynamics.com
License: GNU General Public Licence
Classifier: Framework :: Plone
Classifier: Framework :: Plone :: 6.0
Classifier: Framework :: Plone :: Addon
Classifier: Framework :: Zope
Classifier: Framework :: Zope :: 5
Classifier: License :: OSI Approved :: GNU General Public License (GPL)
Classifier: Programming Language :: Python
Classifier: Programming Language :: Python :: 3.7
Classifier: Programming Language :: Python :: 3.8
Classifier: Programming Language :: Python :: 3.9
Classifier: Programming Language :: Python :: 3.10
Classifier: Topic :: Software Development :: Libraries :: Python Modules
License-File: LICENSE.rst
License-File: LICENSE_GPL.rst
Requires-Dist: bda.plone.ajax
Requires-Dist: bda.plone.cart
Requires-Dist: bda.plone.checkout
Requires-Dist: bda.plone.discount
Requires-Dist: collective.js.datatables
Requires-Dist: plone.restapi
Requires-Dist: Products.CMFPlone
Requires-Dist: pycountry >=23.12.7
Requires-Dist: setuptools
Requires-Dist: simplejson >=2.1
Requires-Dist: six
Requires-Dist: csv23
Requires-Dist: yafowil.plone >2.999
Requires-Dist: yafowil.widget.array
Requires-Dist: yafowil.widget.datetime
Requires-Dist: zope.deferredimport
Provides-Extra: test
Requires-Dist: plone.app.testing ; extra == 'test'
